{"is_source_file": true, "format": "HTML", "description": "This is the main HTML template for a web application, setting up document metadata, including links to fonts, icons, and manifest, and defining the root div for client-side rendering.", "external_files": ["%PUBLIC_URL%/favicon.ico", "%PUBLIC_URL%/logo192.png", "%PUBLIC_URL%/manifest.json"], "external_methods": [], "published": [], "classes": [], "methods": [], "calls": [], "search-terms": ["index.html", "HTML template", "web app setup", "public URL placeholders", "fonts", "favicon", "manifest"], "state": 2, "file_id": 2, "knowledge_revision": 18, "git_revision": "4941a29438649a00fe1f6416f47bd830587f8a51", "hash": "d2b40d02d5f7873d8a6713bad837edd4", "format-version": 4, "code-base-name": "FrontendWebApplication", "filename": "FrontendWebApplication/public/index.html", "revision_history": [{"18": "4941a29438649a00fe1f6416f47bd830587f8a51"}]}